datasette_dateutil/__init__.py
datasette_dateutil-0.3.dist-info/METADATA
datasette_dateutil-0.3.dist-info/WHEEL
datasette_dateutil-0.3.dist-info/entry_points.txt
datasette_dateutil-0.3.dist-info/top_level.txt
datasette_dateutil-0.3.dist-info/RECORD
