Metadata-Version: 2.1
Name: datasette-dateutil
Version: 0.3
Summary: dateutil functions for Datasette
Home-page: https://github.com/simonw/datasette-dateutil
Author: Simon Willison
License: Apache License, Version 2.0
Project-URL: Issues, https://github.com/simonw/datasette-dateutil/issues
Project-URL: CI, https://github.com/simonw/datasette-dateutil/actions
Project-URL: Changelog, https://github.com/simonw/datasette-dateutil/releases
Platform: UNKNOWN
Requires-Dist: datasette
Requires-Dist: python-dateutil
Provides-Extra: test
Requires-Dist: pytest ; extra == 'test'
Requires-Dist: pytest-asyncio ; extra == 'test'
Requires-Dist: httpx ; extra == 'test'
